{
  "code": 0,
  "data": {
    "detail": {
      "records": [
        {
          "fields": {
            "中国电力报得分": 0.5,
            "人民日报得分": 0,
            "其他报刊得分": 4,
            "单位": "本部",
            "品牌社责活动得分": 0,
            "国家电网报得分": 1.5,
            "国网江苏电力服务号得分": 0,
            "央视得分": 5,
            "定性加分": 0,
            "定量扣分": 0,
            "微博发稿得分": 0,
            "总分": 42.1,
            "总分（不含央视）": 37.1,
            "手机报得分": 1,
            "指标修正": 1,
            "新华社得分": 8,
            "查询数据编号": "20260130152243912785139",
            "江苏电力报得分": 7.6,
            "海外传播得分": 0,
            "网省公司网站得分": 10.5,
            "舆情扣分": 0,
            "苏电新闻得分": 0,
            "苏电牛思公众号得分": 2,
            "视频发稿得分": 1
          },
          "id": "FL"
        },
        {
          "fields": {
            "中国电力报得分": 3.5,
            "人民日报得分": 0,
            "其他报刊得分": 5,
            "单位": "东台",
            "品牌社责活动得分": 0.35,
            "国家电网报得分": 0.8,
            "国网江苏电力服务号得分": 0,
            "央视得分": 4,
            "定性加分": 7.8,
            "定量扣分": -3.2,
            "微博发稿得分": 0.9,
            "总分": 40.25,
            "总分（不含央视）": 36.25,
            "手机报得分": 1.1,
            "指标修正": 0.2,
            "新华社得分": 0,
            "江苏电力报得分": 6.2,
            "海外传播得分": 0,
            "网省公司网站得分": 2.6,
            "舆情扣分": 0,
            "苏电新闻得分": 1,
            "苏电牛思公众号得分": 10,
            "视频发稿得分": 0
          },
          "id": "FM"
        },
        {
          "fields": {
            "中国电力报得分": 3.3,
            "人民日报得分": 0,
            "其他报刊得分": 0,
            "单位": "大丰",
            "品牌社责活动得分": 1.9,
            "国家电网报得分": 2.5,
            "国网江苏电力服务号得分": 0,
            "央视得分": 7.5,
            "定性加分": 3.1,
            "定量扣分": -4.2,
            "微博发稿得分": 0.6,
            "总分": 51.6,
            "总分（不含央视）": 25.1,
            "手机报得分": 0.2,
            "指标修正": 23.9,
            "指标修正对冲（央视）": "19",
            "新华社得分": 4,
            "江苏电力报得分": 1.7,
            "海外传播得分": 1.5,
            "网省公司网站得分": 3.6,
            "舆情扣分": 0,
            "苏电新闻得分": 0,
            "苏电牛思公众号得分": 1.7,
            "视频发稿得分": 0.3
          },
          "id": "FN"
        },
        {
          "fields": {
            "中国电力报得分": 1,
            "人民日报得分": 0,
            "其他报刊得分": 4,
            "单位": "建湖",
            "品牌社责活动得分": 1.9,
            "国家电网报得分": 1,
            "国网江苏电力服务号得分": 0,
            "央视得分": 4,
            "定性加分": 12.6,
            "定量扣分": -0.9,
            "微博发稿得分": 1.7,
            "总分": 34.25,
            "总分（不含央视）": 30.25,
            "手机报得分": 0,
            "指标修正": 0,
            "新华社得分": 0,
            "江苏电力报得分": 2.2,
            "海外传播得分": 0,
            "网省公司网站得分": 3.2,
            "舆情扣分": 0,
            "苏电新闻得分": 0,
            "苏电牛思公众号得分": 3.2,
            "视频发稿得分": 0.35
          },
          "id": "FO"
        },
        {
          "fields": {
            "中国电力报得分": 1.6,
            "人民日报得分": 0,
            "其他报刊得分": 4,
            "单位": "射阳",
            "品牌社责活动得分": 2.85,
            "国家电网报得分": 1,
            "国网江苏电力服务号得分": 0,
            "央视得分": 0,
            "定性加分": 11.7,
            "定量扣分": -4.25,
            "微博发稿得分": 0.7,
            "总分": 22.2,
            "总分（不含央视）": 22.2,
            "手机报得分": 1,
            "指标修正": 0.2,
            "新华社得分": 0,
            "江苏电力报得分": 1.4,
            "海外传播得分": 0,
            "网省公司网站得分": 2.3,
            "舆情扣分": -0.5,
            "苏电新闻得分": 0,
            "苏电牛思公众号得分": 0.1,
            "视频发稿得分": 0.1
          },
          "id": "FP"
        },
        {
          "fields": {
            "中国电力报得分": 1.3,
            "人民日报得分": 0,
            "其他报刊得分": 4,
            "单位": "阜宁",
            "品牌社责活动得分": 0.7,
            "国家电网报得分": 0.5,
            "国网江苏电力服务号得分": 0,
            "央视得分": 0,
            "定性加分": 8.3,
            "定量扣分": -3.1,
            "微博发稿得分": 0.5,
            "总分": 16.7,
            "总分（不含央视）": 16.7,
            "手机报得分": 0.4,
            "指标修正": 0,
            "新华社得分": 0,
            "江苏电力报得分": 1,
            "海外传播得分": 0,
            "网省公司网站得分": 1.6,
            "舆情扣分": -0.5,
            "苏电新闻得分": 0,
            "苏电牛思公众号得分": 0,
            "视频发稿得分": 2
          },
          "id": "FQ"
        },
        {
          "fields": {
            "中国电力报得分": 0.8,
            "人民日报得分": 0,
            "其他报刊得分": 0,
            "单位": "滨海",
            "品牌社责活动得分": 2.05,
            "国家电网报得分": 0.5,
            "国网江苏电力服务号得分": 0,
            "央视得分": 4,
            "定性加分": 11.5,
            "定量扣分": -0.65,
            "微博发稿得分": 0.8,
            "总分": 27.9,
            "总分（不含央视）": 21.9,
            "手机报得分": 0.2,
            "指标修正": 2.3,
            "指标修正对冲（央视）": "2",
            "新华社得分": 0,
            "江苏电力报得分": 0.6,
            "海外传播得分": 0,
            "网省公司网站得分": 2.2,
            "舆情扣分": 0,
            "苏电新闻得分": 0,
            "苏电牛思公众号得分": 1.9,
            "视频发稿得分": 1.7
          },
          "id": "FR"
        },
        {
          "fields": {
            "中国电力报得分": 1.5,
            "人民日报得分": 0,
            "其他报刊得分": 4,
            "单位": "响水",
            "品牌社责活动得分": 1.75,
            "国家电网报得分": 0.5,
            "国网江苏电力服务号得分": 0,
            "央视得分": 0,
            "定性加分": 4.1,
            "定量扣分": -2.4,
            "微博发稿得分": 0.8,
            "总分": 19.25,
            "总分（不含央视）": 19.25,
            "手机报得分": 0.2,
            "指标修正": 0.1,
            "新华社得分": 0,
            "江苏电力报得分": 0.5,
            "海外传播得分": 0,
            "网省公司网站得分": 0.7,
            "舆情扣分": -0.5,
            "苏电新闻得分": 0,
            "苏电牛思公众号得分": 7,
            "视频发稿得分": 1
          },
          "id": "FS"
        }
      ]
    },
    "result": "ok"
  },
  "message": "成功"
}
